fount/__init__.py
fount/_exceptions.py
fount/artifact.py
fount/dataset.py
fount/fount.py
fount/jobs.py
fount/models.py
fount/transport.py
fount_core-0.1.7.1.dist-info/licenses/LICENSE
fount_core-0.1.7.1.dist-info/METADATA
fount_core-0.1.7.1.dist-info/WHEEL
fount_core-0.1.7.1.dist-info/top_level.txt
fount_core-0.1.7.1.dist-info/RECORD
