Metadata-Version: 2.4
Name: Fount-Core
Version: 0.1.7.1
Author-email: Bibek Sahu <bibek@datapoem.com>
License-Expression: MIT
Requires-Python: >=3.10
License-File: LICENSE
Requires-Dist: httpx>=0.28.1
Requires-Dist: pandas>=2.3.2
Requires-Dist: pydantic>=2.11.7
Requires-Dist: openpyxl
Dynamic: license-file
